rvc_python/__init__.py
rvc_python/__main__.py
rvc_python/api.py
rvc_python/download_model.py
rvc_python/infer.py
rvc_python/infer_old.py
rvc_python/configs/config.py
rvc_python/configs/v1/32k.json
rvc_python/configs/v1/40k.json
rvc_python/configs/v1/48k.json
rvc_python/configs/v2/32k.json
rvc_python/configs/v2/48k.json
rvc_python/lib/audio.py
rvc_python/lib/rmvpe.py
rvc_python/lib/slicer2.py
rvc_python/lib/globals/globals.py
rvc_python/lib/infer_pack/attentions.py
rvc_python/lib/infer_pack/commons.py
rvc_python/lib/infer_pack/models.py
rvc_python/lib/infer_pack/models_dml.py
rvc_python/lib/infer_pack/models_onnx.py
rvc_python/lib/infer_pack/modules.py
rvc_python/lib/infer_pack/onnx_inference.py
rvc_python/lib/infer_pack/transforms.py
rvc_python/lib/infer_pack/modules/F0Predictor/DioF0Predictor.py
rvc_python/lib/infer_pack/modules/F0Predictor/F0Predictor.py
rvc_python/lib/infer_pack/modules/F0Predictor/HarvestF0Predictor.py
rvc_python/lib/infer_pack/modules/F0Predictor/PMF0Predictor.py
rvc_python/lib/infer_pack/modules/F0Predictor/__init__.py
rvc_python/lib/jit/__init__.py
rvc_python/lib/jit/get_hubert.py
rvc_python/lib/jit/get_rmvpe.py
rvc_python/lib/jit/get_synthesizer.py
rvc_python/modules/ipex/__init__.py
rvc_python/modules/ipex/attention.py
rvc_python/modules/ipex/gradscaler.py
rvc_python/modules/ipex/hijacks.py
rvc_python/modules/onnx/export.py
rvc_python/modules/train/preprocess.py
rvc_python/modules/vc/__init__.py
rvc_python/modules/vc/modules.py
rvc_python/modules/vc/pipeline.py
rvc_python/modules/vc/utils.py
rvc_python-0.1.5.dist-info/METADATA
rvc_python-0.1.5.dist-info/WHEEL
rvc_python-0.1.5.dist-info/licenses/LICENSE
rvc_python-0.1.5.dist-info/RECORD
