Metadata-Version: 2.3
Name: rvc-python
Version: 0.1.5
Summary: Use RVC via console or python scripts
Project-URL: Homepage, https://github.com/daswer123/rvc-python
Project-URL: Bug Tracker, https://github.com/daswer123/rvc-python/issues
Author-email: daswer123 <daswerq123@gmail.com>
License-File: LICENSE
Classifier: License :: OSI Approved :: MIT License
Classifier: Operating System :: OS Independent
Classifier: Programming Language :: Python :: 3
Requires-Python: >=3.9
Requires-Dist: av
Requires-Dist: fairseq==0.12.2
Requires-Dist: faiss-cpu==1.7.3
Requires-Dist: fastapi
Requires-Dist: ffmpeg-python
Requires-Dist: loguru
Requires-Dist: numpy<=1.23.5
Requires-Dist: omegaconf==2.0.6
Requires-Dist: praat-parselmouth>=0.4.2
Requires-Dist: pydantic
Requires-Dist: python-multipart
Requires-Dist: pyworld
Requires-Dist: requests
Requires-Dist: soundfile
Requires-Dist: torch>=2.0.0
Requires-Dist: torchaudio>=2.0.0
Requires-Dist: torchcrepe
Requires-Dist: uvicorn
